cryoCARE-0.2.1.data/scripts/cryoCARE_extract_train_data.py
cryoCARE-0.2.1.data/scripts/cryoCARE_predict.py
cryoCARE-0.2.1.data/scripts/cryoCARE_train.py
cryocare/__init__.py
cryocare/internals/CryoCARE.py
cryocare/internals/CryoCAREDataModule.py
cryocare/internals/__init__.py
cryocare/scripts/__init__.py
cryocare/scripts/cryoCARE_extract_train_data.py
cryocare/scripts/cryoCARE_predict.py
cryocare/scripts/cryoCARE_train.py
cryoCARE-0.2.1.dist-info/LICENSE
cryoCARE-0.2.1.dist-info/METADATA
cryoCARE-0.2.1.dist-info/WHEEL
cryoCARE-0.2.1.dist-info/top_level.txt
cryoCARE-0.2.1.dist-info/RECORD
