Metadata-Version: 2.1
Name: cryoCARE
Version: 0.2.1
Summary: cryoCARE is a deep learning approach for cryo-TEM tomogram denoising.
Home-page: https://github.com/juglab/cryoCARE_pip
Author: Tim-Oliver Buchholz, Thorsten Wagner
Author-email: tim-oliver.buchholz@fmi.ch, thorsten.wagner@mpi-dortmund.mpg.de
Classifier: Programming Language :: Python :: 3
Classifier: Development Status :: 4 - Beta
Classifier: Intended Audience :: Science/Research
Classifier: Topic :: Scientific/Engineering
Classifier: License :: OSI Approved :: BSD License
Requires-Python: >=3.8
License-File: LICENSE
Requires-Dist: numpy
Requires-Dist: mrcfile
Requires-Dist: csbdeep (<0.8.0,>=0.7.0)
Requires-Dist: psutil
